vtext/__init__.py
vtext/_lib.cp36-win_amd64.pyd
vtext/stem.py
vtext/tokenize.py
vtext/tokenize_sentence.py
vtext/vectorize.py
vtext/metrics/__init__.py
vtext/metrics/string.py
vtext/tests/__init__.py
vtext/tests/test_common.py
vtext/tests/test_metrics.py
vtext/tests/test_stem.py
vtext/tests/test_tokenize.py
vtext/tests/test_tokenize_sentence.py
vtext/tests/test_vectorize.py
vtext-0.2.0.dist-info/METADATA
vtext-0.2.0.dist-info/WHEEL
vtext-0.2.0.dist-info/top_level.txt
vtext-0.2.0.dist-info/RECORD
