Metadata-Version: 2.1
Name: vtext
Version: 0.2.0
Summary: Natural Language Processing in Rust with Python bidings
Home-page: https://github.com/rth/vtext
License: Apache License 2.0
Platform: UNKNOWN
Classifier: Programming Language :: Python :: 3
Classifier: Programming Language :: Python :: 3.5
Classifier: Programming Language :: Python :: 3.6
Classifier: Programming Language :: Python :: 3.7
Requires-Python: >=3.6
Requires-Dist: setuptools
Requires-Dist: setuptools-rust (>=0.10.2)
Requires-Dist: numpy (>=1.15.0)
Requires-Dist: scipy (>=1.1.0)
